rokuvim-1.5.2.dist-info/licenses/LICENSE
rv3/__init__.py
rv3/__main__.py
rv3/display.py
rv3/rv3.py
rokuvim-1.5.2.dist-info/METADATA
rokuvim-1.5.2.dist-info/WHEEL
rokuvim-1.5.2.dist-info/entry_points.txt
rokuvim-1.5.2.dist-info/top_level.txt
rokuvim-1.5.2.dist-info/RECORD
