Metadata-Version: 2.4
Name: rokuvim
Version: 1.5.2
Summary: Keyboard-driven Roku remote for the terminal
Author: heheoppsy
Requires-Python: >=3.8
License-File: LICENSE
Requires-Dist: requests>=2.0
Requires-Dist: curtsies
Dynamic: license-file
